{
  "title": "True.Detective.S01E01.720p.HDTV.x264-KILLERS [PublicHD]",
  "uid": 9471724,
  "size": 1744760807,
  "categoryP": "video",
  "categoryS": "hd___tv_shows",
  "magnet": "?xt=urn:btih:0c30eda6b9e3011752a58efe69674402809eb823&amp;dn=True.Detective.S01E01.720p.HDTV.x264-KILLERS+%5BPublicHD%5D&amp;tr=udp%3A%2F%2Ftracker.openbittorrent.com%3A80&amp;tr=udp%3A%2F%2Fopen.demonii.com%3A1337&amp;tr=udp%3A%2F%2Ftracker.coppersurfer.tk%3A6969&amp;tr=udp%3A%2F%2Fexodus.desync.com%3A6969",
  "seeders": 112,
  "leechers": 9,
  "uploader": "DibyaTPB",
  "files": 2,
  "time": 1389595173,
  "description": "\n                PublicHD - High-Definition Bittorrent Community\n      \n                               \n              ----------------------------------------------------\n\nTrue.Detective.S01E01.720p.HDTV.x264-KILLERS [PublicHD]\n \nLength..............: 59mn 42s\nVideo...............: H264 @ 3896Kbps (1280x720)\nFPS.................: 23.976 FPS\nAudio...............: AC3\n\n\n\nSCREENS &lt;a href=&quot;\nhttp://istoreimg.com/i/52d37b37c2c9f.html&quot; rel=&quot;nofollow&quot; target=&quot;_NEW&quot;&gt;\nhttp://istoreimg.com/i/52d37b37c2c9f.html&lt;/a&gt; &lt;a href=&quot;\nhttp://istoreimg.com/i/52d37b3861930.html&quot; rel=&quot;nofollow&quot; target=&quot;_NEW&quot;&gt;\nhttp://istoreimg.com/i/52d37b3861930.html&lt;/a&gt; &lt;a href=&quot;\nhttp://istoreimg.com/i/52d37b38d9e4e.html&quot; rel=&quot;nofollow&quot; target=&quot;_NEW&quot;&gt;\nhttp://istoreimg.com/i/52d37b38d9e4e.html&lt;/a&gt; &lt;a href=&quot;\nhttp://istoreimg.com/i/52d37b396d657.html&quot; rel=&quot;nofollow&quot; target=&quot;_NEW&quot;&gt;\nhttp://istoreimg.com/i/52d37b396d657.html&lt;/a&gt; &lt;a href=&quot;\nhttp://istoreimg.com/i/52d37b39ea217.html&quot; rel=&quot;nofollow&quot; target=&quot;_NEW&quot;&gt;\nhttp://istoreimg.com/i/52d37b39ea217.html&lt;/a&gt; &lt;a href=&quot;\nhttp://istoreimg.com/i/52d37b3a7d058.html&quot; rel=&quot;nofollow&quot; target=&quot;_NEW&quot;&gt;\nhttp://istoreimg.com/i/52d37b3a7d058.html&lt;/a&gt; ",
  "parsed": {
    "xt": "urn:btih:0c30eda6b9e3011752a58efe69674402809eb823",
    "dn": "True.Detective.S01E01.720p.HDTV.x264-KILLERS [PublicHD]",
    "tr": [
      "udp://exodus.desync.com:6969",
      "udp://open.demonii.com:1337",
      "udp://tracker.coppersurfer.tk:6969",
      "udp://tracker.openbittorrent.com:80"
    ],
    "infoHash": "0c30eda6b9e3011752a58efe69674402809eb823",
    "infoHashBuffer": {
      "type": "Buffer",
      "data": [
        12,
        48,
        237,
        166,
        185,
        227,
        1,
        23,
        82,
        165,
        142,
        254,
        105,
        103,
        68,
        2,
        128,
        158,
        184,
        35
      ]
    },
    "name": "True.Detective.S01E01.720p.HDTV.x264-KILLERS [PublicHD]",
    "announce": [
      "udp://exodus.desync.com:6969",
      "udp://open.demonii.com:1337",
      "udp://tracker.coppersurfer.tk:6969",
      "udp://tracker.openbittorrent.com:80"
    ],
    "urlList": []
  },
  "previous": 34,
  "peers": 35,
  "last_updated": "2016-12-26T15:58:50.458Z"
}