{
  "title": "Blackish.S02E19.INTERNAL.HDTV.x264-KILLERS[ettv]",
  "uid": 14220215,
  "size": 183624821,
  "categoryP": "video",
  "categoryS": "tv_shows",
  "magnet": "?xt=urn:btih:0f4eefbb14b213617dd588452af8809245f004fc&amp;dn=Blackish.S02E19.INTERNAL.HDTV.x264-KILLERS%5Bettv%5D&amp;tr=udp%3A%2F%2Ftracker.leechers-paradise.org%3A6969&amp;tr=udp%3A%2F%2Fzer0day.ch%3A1337&amp;tr=udp%3A%2F%2Fopen.demonii.com%3A1337&amp;tr=udp%3A%2F%2Ftracker.coppersurfer.tk%3A6969&amp;tr=udp%3A%2F%2Fexodus.desync.com%3A6969",
  "seeders": 41,
  "leechers": 6,
  "uploader": "ettv",
  "files": 2,
  "time": 1460036296,
  "description": "\nettv - ExtraTorrent TV Shows\r\n\n\nBlackish.S02E19.INTERNAL.HDTV.x264-KILLERS \r\n\n\n[Format]:    Matroska\n[Duration]:    21mn 30s\n[Resolution]:  720 x 404 pixels\n[Display aspect ratio]:    16:9\n[Frame rate mode]:    Constant\n[Frame rate]:    23.976 fps\n\r\n\n#ettv -&gt; To avoid fakes, ALWAYS check that the torrent was added by ettv\r \nhttp://extratorrent.cc/\r\n\n\nHelp us by donating with Bitcoin: 1XeH1kKXWYbzZcFHokGiZ4d3MWW5WyXzU\r\n\nScreens...\r \nhttp://extraimago.com/image/aSBL",
  "parsed": {
    "xt": "urn:btih:0f4eefbb14b213617dd588452af8809245f004fc",
    "dn": "Blackish.S02E19.INTERNAL.HDTV.x264-KILLERS[ettv]",
    "tr": [
      "udp://exodus.desync.com:6969",
      "udp://open.demonii.com:1337",
      "udp://tracker.coppersurfer.tk:6969",
      "udp://tracker.leechers-paradise.org:6969",
      "udp://zer0day.ch:1337"
    ],
    "infoHash": "0f4eefbb14b213617dd588452af8809245f004fc",
    "infoHashBuffer": {
      "type": "Buffer",
      "data": [
        15,
        78,
        239,
        187,
        20,
        178,
        19,
        97,
        125,
        213,
        136,
        69,
        42,
        248,
        128,
        146,
        69,
        240,
        4,
        252
      ]
    },
    "name": "Blackish.S02E19.INTERNAL.HDTV.x264-KILLERS[ettv]",
    "announce": [
      "udp://exodus.desync.com:6969",
      "udp://open.demonii.com:1337",
      "udp://tracker.coppersurfer.tk:6969",
      "udp://tracker.leechers-paradise.org:6969",
      "udp://zer0day.ch:1337"
    ],
    "urlList": []
  },
  "previous": 80,
  "peers": 80,
  "last_updated": "2016-12-26T16:22:00.716Z"
}