{"title":"Red Army (2014) 720p BrRip x264 - YIFY","uid":11954927,"size":735766418,"categoryP":"video","categoryS":"hd___movies","magnet":"?xt=urn:btih:151d7096a2af91abc890c246c645ed3ee9ce0826&amp;dn=Red+Army+%282014%29+720p+BrRip+x264+-+YIFY&amp;tr=udp%3A%2F%2Ftracker.openbittorrent.com%3A80&amp;tr=udp%3A%2F%2Fopen.demonii.com%3A1337&amp;tr=udp%3A%2F%2Ftracker.coppersurfer.tk%3A6969&amp;tr=udp%3A%2F%2Fexodus.desync.com%3A6969","seeders":137,"leechers":6,"uploader":"YIFY","files":2,"time":1432363616,"description":"------------------------------------------------------------------------------- \n ------------------------------------------------------------------------------- \n \n Get all YIFYs newest releases first at http://yts.to/ \n Also there you will find a list of upcoming uploads, instant chat, account registration and an effective movie search. \n \n ------------------------------------------------------------------------------- \n ------------------------------------------------------------------------------- \n  &lt;a href=&quot; http://www.imdb.com/title/tt3264102/&quot; rel=&quot;nofollow&quot; target=&quot;_NEW&quot;&gt; http://www.imdb.com/title/tt3264102/&lt;/a&gt;\n \n \n IMDB RATING: 7.8\n \n FORMAT.......................: MP4\n CODEC........................: X264\n GENRE........................: Documentary / Biography\n FILE SIZE....................: 701.68 MB\n RESOLUTION...................: 1280*720\n FRAME RATE...................: 23.976 fps\n LANGUAGE.....................: English\n RUNTIME......................: 76 mins\n \n \n \n Red Army is a feature documentary about the Soviet Union and the most successful dynasty in sports history: the Red Army hockey team. Told from the perspective of its captain Slava Fetisov, the story portrays his transformation from national hero to political enemy. From the USSR to Russia, the film examines how sport mirrors social and cultural movements and parallels the rise and fall of the Red Army team with the Soviet Union. \n \n SCREEN SHOTS","torrent":{"xt":"urn:btih:151d7096a2af91abc890c246c645ed3ee9ce0826","amp;dn":"Red+Army+%282014%29+720p+BrRip+x264+-+YIFY","amp;tr":["udp%3A%2F%2Ftracker.openbittorrent.com%3A80","udp%3A%2F%2Fopen.demonii.com%3A1337","udp%3A%2F%2Ftracker.coppersurfer.tk%3A6969","udp%3A%2F%2Fexodus.desync.com%3A6969"],"infoHash":"151d7096a2af91abc890c246c645ed3ee9ce0826","infoHashBuffer":{"type":"Buffer","data":[21,29,112,150,162,175,145,171,200,144,194,70,198,69,237,62,233,206,8,38]},"announce":[],"urlList":[]}}