{
  "title": "Fugees - The Score [1996]",
  "uid": 4896972,
  "size": 176570212,
  "categoryP": "audio",
  "categoryS": "music",
  "magnet": "?xt=urn:btih:262453fb04c42cd80d1663523f0b6eb4e03e1d6a&amp;dn=Fugees+-+The+Score+%5B1996%5D&amp;tr=udp%3A%2F%2Ftracker.openbittorrent.com%3A80&amp;tr=udp%3A%2F%2Fopen.demonii.com%3A1337&amp;tr=udp%3A%2F%2Ftracker.coppersurfer.tk%3A6969&amp;tr=udp%3A%2F%2Fexodus.desync.com%3A6969",
  "seeders": 95,
  "leechers": 4,
  "uploader": "TheKyd",
  "files": 18,
  "time": 1242396838,
  "description": "Fugees.The.Score.1996\n\n\n---------------------------------------------------------------------\nTracklisting\n---------------------------------------------------------------------\n\n1. (00:01:52) The Fugees - Red Intro\n2. (00:04:29) The Fugees - How Many Mics\n3. (00:03:47) The Fugees - Ready or Not\n4. (00:04:21) The Fugees - Zealots\n5. (00:05:37) The Fugees - The Beast\n6. (00:04:20) The Fugees - Fu-Gee-La\n7. (00:05:44) The Fugees - Family Business\n8. (00:04:59) The Fugees - Killing Me Softly with His Song\n9. (00:05:02) The Fugees - The Score\n10. (00:04:51) The Fugees - The Mask\n11. (00:05:23) The Fugees - Cowboys\n12. (00:04:33) The Fugees - No Woman, No Cry\n13. (00:06:00) The Fugees - Manifest/Outro\n14. (00:04:24) The Fugees - Fu-Gee-La (Refugee camp remix)\n15. (00:05:27) The Fugees - Fu-Gee-La (Sly and Robbie mix)\n16. (00:02:43) The Fugees - Mista Mista\n\nPlaying Time........: 01:13:30\nQuality................: bitrate: 320kbps\nTotal Size............: 168.37 MB\nInfoHash.............:262453FB04C42CD80D1663523F0B6EB4E03E1D6A",
  "parsed": {
    "xt": "urn:btih:262453fb04c42cd80d1663523f0b6eb4e03e1d6a",
    "dn": "Fugees - The Score [1996]",
    "tr": [
      "udp://exodus.desync.com:6969",
      "udp://open.demonii.com:1337",
      "udp://tracker.coppersurfer.tk:6969",
      "udp://tracker.openbittorrent.com:80"
    ],
    "infoHash": "262453fb04c42cd80d1663523f0b6eb4e03e1d6a",
    "infoHashBuffer": {
      "type": "Buffer",
      "data": [
        38,
        36,
        83,
        251,
        4,
        196,
        44,
        216,
        13,
        22,
        99,
        82,
        63,
        11,
        110,
        180,
        224,
        62,
        29,
        106
      ]
    },
    "name": "Fugees - The Score [1996]",
    "announce": [
      "udp://exodus.desync.com:6969",
      "udp://open.demonii.com:1337",
      "udp://tracker.coppersurfer.tk:6969",
      "udp://tracker.openbittorrent.com:80"
    ],
    "urlList": []
  },
  "previous": 50,
  "peers": 50,
  "last_updated": "2016-12-26T19:17:55.449Z"
}