{
  "title": "The Big Bang Theory S08E17 HDTV x264-LOL [eztv]",
  "uid": 11737624,
  "size": 119530496,
  "categoryP": "video",
  "categoryS": "tv_shows",
  "magnet": "?xt=urn:btih:2ac66a3a047fb0c2ee2defd15095c90c8b50dc20&amp;dn=The+Big+Bang+Theory+S08E17+HDTV+x264-LOL+%5Beztv%5D&amp;tr=udp%3A%2F%2Ftracker.openbittorrent.com%3A80&amp;tr=udp%3A%2F%2Fopen.demonii.com%3A1337&amp;tr=udp%3A%2F%2Ftracker.coppersurfer.tk%3A6969&amp;tr=udp%3A%2F%2Fexodus.desync.com%3A6969",
  "seeders": 491,
  "leechers": 36,
  "uploader": "eztv",
  "files": 1,
  "time": 1425619752,
  "description": "Help us by donating with Bitcoin: 1EZTVaGQ6UsjYJ9fwqGnd45oZ6HGT7WKZd\n\n#EZTV -&gt; To avoid fakes, ALWAYS check that the torrent was added by eztv. &lt;a href=&quot;\nhttps://eztv.ch/&quot; rel=&quot;nofollow&quot; target=&quot;_NEW&quot;&gt;\nhttps://eztv.ch/&lt;/a&gt; (WARNING. THIS DOMAIN HAS BEEN TAKEN OVER BY SCAMMERS. STAY AWAY)\n\nEpisode: The Big Bang Theory S08E17 HDTV x264-LOL\nScreenshots: &lt;a href=&quot;\nhttps://ezimg.it/th/f9b7b60ffe6db77510ac8f3287ae613d/69d7f8e08846f11843f1aed5647286b4c58af4de.png&quot; rel=&quot;nofollow&quot; target=&quot;_NEW&quot;&gt;\nhttps://ezimg.it/th/f9b7b60ffe6db77510ac8f3287ae613d/69d7f8e08846f11843f1aed5647286b4c58af4de.png&lt;/a&gt;\n",
  "parsed": {
    "xt": "urn:btih:2ac66a3a047fb0c2ee2defd15095c90c8b50dc20",
    "dn": "The Big Bang Theory S08E17 HDTV x264-LOL [eztv]",
    "tr": [
      "udp://exodus.desync.com:6969",
      "udp://open.demonii.com:1337",
      "udp://tracker.coppersurfer.tk:6969",
      "udp://tracker.openbittorrent.com:80"
    ],
    "infoHash": "2ac66a3a047fb0c2ee2defd15095c90c8b50dc20",
    "infoHashBuffer": {
      "type": "Buffer",
      "data": [
        42,
        198,
        106,
        58,
        4,
        127,
        176,
        194,
        238,
        45,
        239,
        209,
        80,
        149,
        201,
        12,
        139,
        80,
        220,
        32
      ]
    },
    "name": "The Big Bang Theory S08E17 HDTV x264-LOL [eztv]",
    "announce": [
      "udp://exodus.desync.com:6969",
      "udp://open.demonii.com:1337",
      "udp://tracker.coppersurfer.tk:6969",
      "udp://tracker.openbittorrent.com:80"
    ],
    "urlList": []
  },
  "previous": 106,
  "peers": 186,
  "last_updated": "2016-12-26T19:53:08.083Z"
}