{
  "title": "[HorribleSubs] World Trigger - 02 [720p]",
  "uid": 11195318,
  "size": 332772973,
  "categoryP": "video",
  "categoryS": "hd___tv_shows",
  "magnet": "?xt=urn:btih:2b4a371250f97db36a675fe9301e4d47505785e5&amp;dn=%5BHorribleSubs%5D+World+Trigger+-+02+%5B720p%5D&amp;tr=udp%3A%2F%2Ftracker.openbittorrent.com%3A80&amp;tr=udp%3A%2F%2Fopen.demonii.com%3A1337&amp;tr=udp%3A%2F%2Ftracker.coppersurfer.tk%3A6969&amp;tr=udp%3A%2F%2Fexodus.desync.com%3A6969",
  "seeders": 61,
  "leechers": 1,
  "uploader": "Ralphless",
  "files": -1,
  "time": 1413079741,
  "description": "World Trigger - 02\n\nQuality : 720p\n\nAudio : Japanese\n\nSubtitles : English by Horrible Subs\n\nFormat : MKV",
  "parsed": {
    "xt": "urn:btih:2b4a371250f97db36a675fe9301e4d47505785e5",
    "dn": "[HorribleSubs] World Trigger - 02 [720p]",
    "tr": [
      "udp://exodus.desync.com:6969",
      "udp://open.demonii.com:1337",
      "udp://tracker.coppersurfer.tk:6969",
      "udp://tracker.openbittorrent.com:80"
    ],
    "infoHash": "2b4a371250f97db36a675fe9301e4d47505785e5",
    "infoHashBuffer": {
      "type": "Buffer",
      "data": [
        43,
        74,
        55,
        18,
        80,
        249,
        125,
        179,
        106,
        103,
        95,
        233,
        48,
        30,
        77,
        71,
        80,
        87,
        133,
        229
      ]
    },
    "name": "[HorribleSubs] World Trigger - 02 [720p]",
    "announce": [
      "udp://exodus.desync.com:6969",
      "udp://open.demonii.com:1337",
      "udp://tracker.coppersurfer.tk:6969",
      "udp://tracker.openbittorrent.com:80"
    ],
    "urlList": []
  },
  "previous": 12,
  "peers": 21,
  "last_updated": "2016-12-26T19:56:44.769Z"
}