{"title":"My Dirty Hobby - Lucy Cat - Latex ass anal challenge","uid":15824003,"size":148948793,"categoryP":"porn","categoryS":"other","magnet":"?xt=urn:btih:3c0ffa9f576461470f0346f29306cb286e9354b9&amp;dn=My+Dirty+Hobby+-+Lucy+Cat+-+Latex+ass+anal+challenge&amp;tr=udp%3A%2F%2Ftracker.leechers-paradise.org%3A6969&amp;tr=udp%3A%2F%2Fzer0day.ch%3A1337&amp;tr=udp%3A%2F%2Fopen.demonii.com%3A1337&amp;tr=udp%3A%2F%2Ftracker.coppersurfer.tk%3A6969&amp;tr=udp%3A%2F%2Fexodus.desync.com%3A6969","seeders":37,"leechers":3,"uploader":"shtihl22","files":1,"time":1473809766,"description":"**********Description***********\r\n\r\n \nhttp://imagebic.com/?g=999117 \nhttp://imagebic.com/?v=424554\r\n\r\n=======================================\r\n \nhttps://thepiratebay.org/user/shtihl22\r\n\r\n=======================================","torrent":{"xt":"urn:btih:3c0ffa9f576461470f0346f29306cb286e9354b9","amp;dn":"My+Dirty+Hobby+-+Lucy+Cat+-+Latex+ass+anal+challenge","amp;tr":["udp%3A%2F%2Ftracker.leechers-paradise.org%3A6969","udp%3A%2F%2Fzer0day.ch%3A1337","udp%3A%2F%2Fopen.demonii.com%3A1337","udp%3A%2F%2Ftracker.coppersurfer.tk%3A6969","udp%3A%2F%2Fexodus.desync.com%3A6969"],"infoHash":"3c0ffa9f576461470f0346f29306cb286e9354b9","infoHashBuffer":{"type":"Buffer","data":[60,15,250,159,87,100,97,71,15,3,70,242,147,6,203,40,110,147,84,185]},"announce":[],"urlList":[]}}