{"title":"The Bold And The Beautiful - S30 Ep7427 - 2016-09-26","uid":15901340,"size":593294406,"categoryP":"video","categoryS":"tv_shows","magnet":"?xt=urn:btih:4be415e9b7c9a71a17b70654fb5c1e4200079cd1&amp;dn=The+Bold+And+The+Beautiful+-+S30+Ep7427+-+2016-09-26&amp;tr=udp%3A%2F%2Ftracker.leechers-paradise.org%3A6969&amp;tr=udp%3A%2F%2Fzer0day.ch%3A1337&amp;tr=udp%3A%2F%2Fopen.demonii.com%3A1337&amp;tr=udp%3A%2F%2Ftracker.coppersurfer.tk%3A6969&amp;tr=udp%3A%2F%2Fexodus.desync.com%3A6969","seeders":38,"leechers":10,"uploader":"gurfel65","files":5,"time":1475014446,"description":"Ridge stands firm with his siblings when their support of him begins to waiver","torrent":{"xt":"urn:btih:4be415e9b7c9a71a17b70654fb5c1e4200079cd1","amp;dn":"The+Bold+And+The+Beautiful+-+S30+Ep7427+-+2016-09-26","amp;tr":["udp%3A%2F%2Ftracker.leechers-paradise.org%3A6969","udp%3A%2F%2Fzer0day.ch%3A1337","udp%3A%2F%2Fopen.demonii.com%3A1337","udp%3A%2F%2Ftracker.coppersurfer.tk%3A6969","udp%3A%2F%2Fexodus.desync.com%3A6969"],"infoHash":"4be415e9b7c9a71a17b70654fb5c1e4200079cd1","infoHashBuffer":{"type":"Buffer","data":[75,228,21,233,183,201,167,26,23,183,6,84,251,92,30,66,0,7,156,209]},"announce":[],"urlList":[]}}