{
  "title": "Nicci French - Denken aan vrijdag. NL Ebook. DMT ",
  "uid": 11796052,
  "size": 628610,
  "categoryP": "other",
  "categoryS": "e_books",
  "magnet": "?xt=urn:btih:5ada2d44cf9269d03f9908620899a87c5ccccebb&amp;dn=Nicci+French+-+Denken+aan+vrijdag.+NL+Ebook.+DMT+&amp;tr=udp%3A%2F%2Ftracker.openbittorrent.com%3A80&amp;tr=udp%3A%2F%2Fopen.demonii.com%3A1337&amp;tr=udp%3A%2F%2Ftracker.coppersurfer.tk%3A6969&amp;tr=udp%3A%2F%2Fexodus.desync.com%3A6969",
  "seeders": 145,
  "leechers": 26,
  "uploader": "BiWild",
  "files": 4,
  "time": 1428173483,
  "description": "Nicci French - Denken aan vrijdag. NL Ebook. DMT \n\nAfbeelding\n\nAuteur: Nicci French\nPagina's: 268\nTaal: Dutch/Nederlands\nUitgever: Ambo/Anthos B.V\nJaar van uitgifte: 2015\nGenre: Thriller\n\nSamenvatting\n\nNicci French - Denken aan vrijdag\nUit de Thames wordt het lijk van een man met doorgesneden keel gevist. Hij is onherkenbaar, want hij heeft al een tijd \nin het water gelegen. Het enige aanknopingspunt is een ziekenhuisbandje om zijn pols met daarop de naam Frieda Klein.\nAlgauw blijkt dat psychotherapeute Frieda Klein een wel erg persoonlijke band met het slachtoffer had en wordt ze als \nde belangrijkste verdachte van het misdrijf gezien. Frieda heeft vanwege haar verleden weinig goodwill bij het politiekorps,\nmaar gelukkig heeft ze vrienden die bereid zijn om tot het uiterste voor haar te gaan...\n\nMet dank aan de originele poster !!\n\nDeze review wordt u aangeboden door\n\nDUTCH MOVIE THEATER",
  "parsed": {
    "xt": "urn:btih:5ada2d44cf9269d03f9908620899a87c5ccccebb",
    "dn": "Nicci French - Denken aan vrijdag. NL Ebook. DMT ",
    "tr": [
      "udp://exodus.desync.com:6969",
      "udp://open.demonii.com:1337",
      "udp://tracker.coppersurfer.tk:6969",
      "udp://tracker.openbittorrent.com:80"
    ],
    "infoHash": "5ada2d44cf9269d03f9908620899a87c5ccccebb",
    "infoHashBuffer": {
      "type": "Buffer",
      "data": [
        90,
        218,
        45,
        68,
        207,
        146,
        105,
        208,
        63,
        153,
        8,
        98,
        8,
        153,
        168,
        124,
        92,
        204,
        206,
        187
      ]
    },
    "name": "Nicci French - Denken aan vrijdag. NL Ebook. DMT ",
    "announce": [
      "udp://exodus.desync.com:6969",
      "udp://open.demonii.com:1337",
      "udp://tracker.coppersurfer.tk:6969",
      "udp://tracker.openbittorrent.com:80"
    ],
    "urlList": []
  },
  "previous": 171,
  "peers": 19,
  "last_updated": "2016-12-25T02:02:41.834Z"
}