{"title":"Calvin Harris - Blame (feat. John Newman) [EDM RG]","uid":11004209,"size":8864220,"categoryP":"audio","categoryS":"music","magnet":"?xt=urn:btih:73b42a6bd63581e43355ce5a10710be3f017a199&amp;dn=Calvin+Harris+-+Blame+%28feat.+John+Newman%29+%5BEDM+RG%5D&amp;tr=udp%3A%2F%2Ftracker.openbittorrent.com%3A80&amp;tr=udp%3A%2F%2Fopen.demonii.com%3A1337&amp;tr=udp%3A%2F%2Ftracker.coppersurfer.tk%3A6969&amp;tr=udp%3A%2F%2Fexodus.desync.com%3A6969","seeders":202,"leechers":7,"uploader":"Drone123","files":-1,"time":1410195141,"description":"Calvin Harris - Blame (feat. John Newman)\n\nArtist/Performer : Calvin Harris\nAlbum : Blame (feat. John Newman) - Single\nDuration : 3m 34s\nGenre: Dance\nRelease Date: September 7, 2014\nSource: iTunes\n\nFile size : 8,45 MB\nOverall bit rate : 320 Kbps (.mp3)\nChannels: Joint Stereo\nSample rate: 44.1 kHZ\n\n\nNote:\nArtwork included, organized and iTunes ready.","torrent":{"xt":"urn:btih:73b42a6bd63581e43355ce5a10710be3f017a199","amp;dn":"Calvin+Harris+-+Blame+%28feat.+John+Newman%29+%5BEDM+RG%5D","amp;tr":["udp%3A%2F%2Ftracker.openbittorrent.com%3A80","udp%3A%2F%2Fopen.demonii.com%3A1337","udp%3A%2F%2Ftracker.coppersurfer.tk%3A6969","udp%3A%2F%2Fexodus.desync.com%3A6969"],"infoHash":"73b42a6bd63581e43355ce5a10710be3f017a199","infoHashBuffer":{"type":"Buffer","data":[115,180,42,107,214,53,129,228,51,85,206,90,16,113,11,227,240,23,161,153]},"announce":[],"urlList":[]}}