{
  "title": "Tom Jones - Greatest Hits - The Platinum Edition",
  "uid": 3926743,
  "size": 151463387,
  "categoryP": "audio",
  "categoryS": "music",
  "magnet": "?xt=urn:btih:7ca1cb03f4e45145f7e4705e530356e0160e588a&amp;dn=Tom+Jones+-+Greatest+Hits+-+The+Platinum+Edition&amp;tr=udp%3A%2F%2Ftracker.openbittorrent.com%3A80&amp;tr=udp%3A%2F%2Fopen.demonii.com%3A1337&amp;tr=udp%3A%2F%2Ftracker.coppersurfer.tk%3A6969&amp;tr=udp%3A%2F%2Fexodus.desync.com%3A6969",
  "seeders": 39,
  "leechers": 3,
  "uploader": "cholo24",
  "files": 24,
  "time": 1197143476,
  "description": "Tom Jones - Greatest Hits\nThe Platinum Edition\n\n01. It&amp;#039;s Not Unusual \n02. What&amp;#039;s New Pussycat \n03. Green Green Grass Of Home \n04. Delilah \n05. Funny Familiar Forgotten Feelings \n06. I&amp;#039;ll Never Fall In Love Again \n07. I&amp;#039;m Coming Home \n08. Help Yourself \n09. Love Me Tonight \n10. She&amp;#039;s A Lady \n11. Thunderball \n12. Daughter Of Darkness \n13. If I Only Knew \n14. Till \n15. Young New Mexican Puppeteer \n16. Boy From Nowhere \n17. Kiss - Art Of Noise &amp; Tom Jones \n18. Burning Down The House - Jones, Tom &amp; Cardigans \n19. Baby It&amp;#039;s Cold Outside - Jones, Tom &amp; Cerys Matthews \n20. Mama Told Me Not To Come - Jones, Tom &amp; Stereophonics \n21. Sexbomb - Jones, Tom &amp; Mousse T \n22. Full Monty Medley - Jones, Tom &amp; Robbie Williams \n23. Stoned In Love - Chicane &amp; Tom Jon\n",
  "parsed": {
    "xt": "urn:btih:7ca1cb03f4e45145f7e4705e530356e0160e588a",
    "dn": "Tom Jones - Greatest Hits - The Platinum Edition",
    "tr": [
      "udp://exodus.desync.com:6969",
      "udp://open.demonii.com:1337",
      "udp://tracker.coppersurfer.tk:6969",
      "udp://tracker.openbittorrent.com:80"
    ],
    "infoHash": "7ca1cb03f4e45145f7e4705e530356e0160e588a",
    "infoHashBuffer": {
      "type": "Buffer",
      "data": [
        124,
        161,
        203,
        3,
        244,
        228,
        81,
        69,
        247,
        228,
        112,
        94,
        83,
        3,
        86,
        224,
        22,
        14,
        88,
        138
      ]
    },
    "name": "Tom Jones - Greatest Hits - The Platinum Edition",
    "announce": [
      "udp://exodus.desync.com:6969",
      "udp://open.demonii.com:1337",
      "udp://tracker.coppersurfer.tk:6969",
      "udp://tracker.openbittorrent.com:80"
    ],
    "urlList": []
  },
  "previous": 42,
  "peers": 43,
  "last_updated": "2016-12-25T05:41:58.203Z"
}