{
  "title": "Closer.To.God.2014.HDRip.XviD-EVO",
  "uid": 11991609,
  "size": 812882981,
  "categoryP": "video",
  "categoryS": "movies",
  "magnet": "?xt=urn:btih:8f0f7785a93319bc17dfd538982f7415805e98b6&amp;dn=Closer.To.God.2014.HDRip.XviD-EVO&amp;tr=udp%3A%2F%2Ftracker.openbittorrent.com%3A80&amp;tr=udp%3A%2F%2Fopen.demonii.com%3A1337&amp;tr=udp%3A%2F%2Ftracker.coppersurfer.tk%3A6969&amp;tr=udp%3A%2F%2Fexodus.desync.com%3A6969",
  "seeders": 36,
  "leechers": 14,
  "uploader": "xxxlavalxxx",
  "files": 4,
  "time": 1433526078,
  "description": " &lt;a href=&quot;http://extraimago.com/image/TBA&quot; rel=&quot;nofollow&quot; target=&quot;_NEW&quot;&gt;http://extraimago.com/image/TBA&lt;/a&gt;\n &lt;a href=&quot;\nhttp://www.imdb.com/title/tt3457486/&quot; rel=&quot;nofollow&quot; target=&quot;_NEW&quot;&gt;\nhttp://www.imdb.com/title/tt3457486/&lt;/a&gt;\n\n\nA genetic scientist successfully clones the first human being, a baby girl named Elizabeth, but his work is soon threatened by a dark secret, a secret that threatens to destroy everything and everyone precious to him.\n\nDirector: Billy Senese\nWriter: Billy Senese\nStars: Jeremy Childs, Shelean Newman, Shannon Hoppe \nGenres: Horror | Sci-Fi | Thriller\nCountry: USA\nLanguage: English\n\n\nRELEASE: Closer.To.God.2014.HDRip.XviD-EVO\n\n SOURCE: 720p WEBRip - Thanks friend!\n\n ViDEO: 1194 Kbps  XviD\n\n RESOLUTiON: 720 x 304\n\n RUNTiME: 1h 20mn 39s\n\n SUBTiTLES: N/A\n\n Audio: 128 Kbps MP3\n\n LANGUAGE: ENGLiSH \n\n NOTES:   \n         Enjoy ^^\n\nGreetz : AQOS\n\n &lt;a href=&quot;\nhttp://extraimago.com/image/TBW&quot; rel=&quot;nofollow&quot; target=&quot;_NEW&quot;&gt;\nhttp://extraimago.com/image/TBW&lt;/a&gt; &lt;a href=&quot;\nhttp://extraimago.com/image/TBf&quot; rel=&quot;nofollow&quot; target=&quot;_NEW&quot;&gt;\nhttp://extraimago.com/image/TBf&lt;/a&gt; &lt;a href=&quot;\nhttp://extraimago.com/image/TC8&quot; rel=&quot;nofollow&quot; target=&quot;_NEW&quot;&gt;\nhttp://extraimago.com/image/TC8&lt;/a&gt;",
  "parsed": {
    "xt": "urn:btih:8f0f7785a93319bc17dfd538982f7415805e98b6",
    "dn": "Closer.To.God.2014.HDRip.XviD-EVO",
    "tr": [
      "udp://exodus.desync.com:6969",
      "udp://open.demonii.com:1337",
      "udp://tracker.coppersurfer.tk:6969",
      "udp://tracker.openbittorrent.com:80"
    ],
    "infoHash": "8f0f7785a93319bc17dfd538982f7415805e98b6",
    "infoHashBuffer": {
      "type": "Buffer",
      "data": [
        143,
        15,
        119,
        133,
        169,
        51,
        25,
        188,
        23,
        223,
        213,
        56,
        152,
        47,
        116,
        21,
        128,
        94,
        152,
        182
      ]
    },
    "name": "Closer.To.God.2014.HDRip.XviD-EVO",
    "announce": [
      "udp://exodus.desync.com:6969",
      "udp://open.demonii.com:1337",
      "udp://tracker.coppersurfer.tk:6969",
      "udp://tracker.openbittorrent.com:80"
    ],
    "urlList": []
  },
  "previous": 4,
  "peers": 4,
  "last_updated": "2016-12-27T06:48:48.514Z"
}