{"title":"FSET-648 No Is Out Absolute Voice!","uid":15793187,"size":1397961146,"categoryP":"porn","categoryS":"movie_clips","magnet":"?xt=urn:btih:9d8c4cd8dcd69b0b828786f898cbda7a73b79265&amp;dn=FSET-648+No+Is+Out+Absolute+Voice%21&amp;tr=udp%3A%2F%2Ftracker.leechers-paradise.org%3A6969&amp;tr=udp%3A%2F%2Fzer0day.ch%3A1337&amp;tr=udp%3A%2F%2Fopen.demonii.com%3A1337&amp;tr=udp%3A%2F%2Ftracker.coppersurfer.tk%3A6969&amp;tr=udp%3A%2F%2Fexodus.desync.com%3A6969","seeders":48,"leechers":16,"uploader":"texile911","files":1,"time":1473411327,"description":"http://imgplus.ru/img-57d25cfc01ca8.html \nhttp://imgplus.ru/img-57d25cfc0c9db.html","torrent":{"xt":"urn:btih:9d8c4cd8dcd69b0b828786f898cbda7a73b79265","amp;dn":"FSET-648+No+Is+Out+Absolute+Voice%21","amp;tr":["udp%3A%2F%2Ftracker.leechers-paradise.org%3A6969","udp%3A%2F%2Fzer0day.ch%3A1337","udp%3A%2F%2Fopen.demonii.com%3A1337","udp%3A%2F%2Ftracker.coppersurfer.tk%3A6969","udp%3A%2F%2Fexodus.desync.com%3A6969"],"infoHash":"9d8c4cd8dcd69b0b828786f898cbda7a73b79265","infoHashBuffer":{"type":"Buffer","data":[157,140,76,216,220,214,155,11,130,135,134,248,152,203,218,122,115,183,146,101]},"announce":[],"urlList":[]}}