{"title":"WWE Clash of Champions 2016 720p HDTV x264-Ebi [TJET]","uid":15897248,"size":6605028658,"categoryP":"video","categoryS":"hd___tv_shows","magnet":"?xt=urn:btih:ae02f78c835108bd9212167e81d8bd4ad102b8ef&amp;dn=WWE+Clash+of+Champions+2016+720p+HDTV+x264-Ebi+%5BTJET%5D&amp;tr=udp%3A%2F%2Ftracker.leechers-paradise.org%3A6969&amp;tr=udp%3A%2F%2Fzer0day.ch%3A1337&amp;tr=udp%3A%2F%2Fopen.demonii.com%3A1337&amp;tr=udp%3A%2F%2Ftracker.coppersurfer.tk%3A6969&amp;tr=udp%3A%2F%2Fexodus.desync.com%3A6969","seeders":119,"leechers":139,"uploader":"CenaCme","files":2,"time":1474972712,"description":"WWE.Clash.of.Champions.2016.720p.HDTV.x264-Ebi\r\nRelease Info:\r\nShow Name: WWE Clash of Champions 2016\r\nGenre: Wrestling\r\nRelease Date: 2016-09-26(UK)\r\nAir Date: 2016-09-25(US)\r\nSource : HDTV\r\nContainer: MP4\r\nVideo: x264, 4702Kbps, 29,970fps, 1280x720, 16:9\r\nAudio: AAC, 192Kbps, 48KHz, 2ch\r\nSize: 6.15 GB\r\nRuntime: 3h 07mn 18s\r\n\r\n\r\nThumb sheet:\r\n \nhttps://extraimago.com/image/wMme","torrent":{"xt":"urn:btih:ae02f78c835108bd9212167e81d8bd4ad102b8ef","amp;dn":"WWE+Clash+of+Champions+2016+720p+HDTV+x264-Ebi+%5BTJET%5D","amp;tr":["udp%3A%2F%2Ftracker.leechers-paradise.org%3A6969","udp%3A%2F%2Fzer0day.ch%3A1337","udp%3A%2F%2Fopen.demonii.com%3A1337","udp%3A%2F%2Ftracker.coppersurfer.tk%3A6969","udp%3A%2F%2Fexodus.desync.com%3A6969"],"infoHash":"ae02f78c835108bd9212167e81d8bd4ad102b8ef","infoHashBuffer":{"type":"Buffer","data":[174,2,247,140,131,81,8,189,146,18,22,126,129,216,189,74,209,2,184,239]},"announce":[],"urlList":[]}}