{
  "title": "Tufos - Familia Sacana 1-11 (Bastard Family) (English Version)",
  "uid": 14434655,
  "size": 48237404,
  "categoryP": "porn",
  "categoryS": "other",
  "magnet": "?xt=urn:btih:b3c136bde1a8edb484e3f968b8c442c717e2a43d&amp;dn=Tufos+-+Familia+Sacana+1-11+%28Bastard+Family%29+%28English+Version%29+&amp;tr=udp%3A%2F%2Ftracker.leechers-paradise.org%3A6969&amp;tr=udp%3A%2F%2Fzer0day.ch%3A1337&amp;tr=udp%3A%2F%2Fopen.demonii.com%3A1337&amp;tr=udp%3A%2F%2Ftracker.coppersurfer.tk%3A6969&amp;tr=udp%3A%2F%2Fexodus.desync.com%3A6969",
  "seeders": 37,
  "leechers": 3,
  "uploader": "almeris",
  "files": 5,
  "time": 1461630481,
  "description": "Size: 46 MB - Type: Full Color \r\n \r\nFormat: CBR - Resolution: 700x900 Aprox.   \r\n\r\nContains: 109 Pages - Language: English\r\n\r\n \nhttp://postimg.org/image/9xm80odar/\r\n \nhttp://postimg.org/image/rc6g8yafn/\r\n \nhttp://postimg.org/image/foceeelar/",
  "parsed": {
    "xt": "urn:btih:b3c136bde1a8edb484e3f968b8c442c717e2a43d",
    "dn": "Tufos - Familia Sacana 1-11 (Bastard Family) (English Version) ",
    "tr": [
      "udp://exodus.desync.com:6969",
      "udp://open.demonii.com:1337",
      "udp://tracker.coppersurfer.tk:6969",
      "udp://tracker.leechers-paradise.org:6969",
      "udp://zer0day.ch:1337"
    ],
    "infoHash": "b3c136bde1a8edb484e3f968b8c442c717e2a43d",
    "infoHashBuffer": {
      "type": "Buffer",
      "data": [
        179,
        193,
        54,
        189,
        225,
        168,
        237,
        180,
        132,
        227,
        249,
        104,
        184,
        196,
        66,
        199,
        23,
        226,
        164,
        61
      ]
    },
    "name": "Tufos - Familia Sacana 1-11 (Bastard Family) (English Version) ",
    "announce": [
      "udp://exodus.desync.com:6969",
      "udp://open.demonii.com:1337",
      "udp://tracker.coppersurfer.tk:6969",
      "udp://tracker.leechers-paradise.org:6969",
      "udp://zer0day.ch:1337"
    ],
    "urlList": []
  },
  "previous": 58,
  "peers": 27,
  "last_updated": "2016-12-27T10:44:35.117Z"
}