{
  "title": "The.Boy.Next.Door.2015.BRRip.XviD-ETRG",
  "uid": 11819136,
  "size": 743435339,
  "categoryP": "video",
  "categoryS": "movies",
  "magnet": "?xt=urn:btih:b4e09be176781fd49d9babfa3f0aa17d70e289e6&amp;dn=The.Boy.Next.Door.2015.BRRip.XviD-ETRG&amp;tr=udp%3A%2F%2Ftracker.openbittorrent.com%3A80&amp;tr=udp%3A%2F%2Fopen.demonii.com%3A1337&amp;tr=udp%3A%2F%2Ftracker.coppersurfer.tk%3A6969&amp;tr=udp%3A%2F%2Fexodus.desync.com%3A6969",
  "seeders": 120,
  "leechers": 54,
  "uploader": "SaM",
  "files": 6,
  "time": 1429220718,
  "description": " The.Boy.Next.Door.2015.BRRip.XviD-ETRG      \n\nTheatre Date     : 23 January 2015 (USA)               \niMDB User Ratings: 4.4                                 \nGenre            : Thriller                            \niMDB Link        : http://www.imdb.com/title/tt3181822/\n\nVIDEO :-                                   \n                                           \nFormat          :  Audio Video Interleave \nBitrate         :  940  kbps              \nCodec ID        :  XviD                   \nResolution      :  640 X 272              \nAspect Ratio    :  2.35:1                 \nFrame Rate      :  23.976 fps             \nQuality Frame   :  0.225                       \n\nAudio :-\n                      \nCodec ID        :   MP3       \nBitrate         :   128 kbps  \nChannel(s)      :   2         \nSample Rate     :   48.0 KHZ  \n                                              \nEncoder         :   SaM                     \nFile Size       :   699 MiB                 \nDuration        :   01h30m                  \nSource          :   BluRay SPARKS (Thanks)  \nRelease Date    :   16-04-2015              \nLanguage        :   English                 \nSubtitles       :   English                 \nSample          :   Yes                                                                                              \n\nCast:-\n\nJennifer Lopez        :       Claire Peterson \nRyan Guzman           :       Noah Sandborn   \n\nPlot:-\n\nA newly divorced woman falls for a younger man who has\nrecently moved in across the street from her,but their\ntorrid affair soon takes a dangerous turn.            \n\nScreens:-\n &lt;a href=&quot;\nhttp://extraimago.com/image/wZL&quot; rel=&quot;nofollow&quot; target=&quot;_NEW&quot;&gt;\nhttp://extraimago.com/image/wZL&lt;/a&gt; &lt;a href=&quot;\nhttp://extraimago.com/image/wZQ&quot; rel=&quot;nofollow&quot; target=&quot;_NEW&quot;&gt;\nhttp://extraimago.com/image/wZQ&lt;/a&gt; &lt;a href=&quot;\nhttp://extraimago.com/image/wZR&quot; rel=&quot;nofollow&quot; target=&quot;_NEW&quot;&gt;\nhttp://extraimago.com/image/wZR&lt;/a&gt; &lt;a href=&quot;\nhttp://extraimago.com/image/wZm&quot; rel=&quot;nofollow&quot; target=&quot;_NEW&quot;&gt;\nhttp://extraimago.com/image/wZm&lt;/a&gt; &lt;a href=&quot;\nhttp://extraimago.com/image/wZi&quot; rel=&quot;nofollow&quot; target=&quot;_NEW&quot;&gt;\nhttp://extraimago.com/image/wZi&lt;/a&gt; &lt;a href=&quot;\nhttp://extraimago.com/image/wZl&quot; rel=&quot;nofollow&quot; target=&quot;_NEW&quot;&gt;\nhttp://extraimago.com/image/wZl&lt;/a&gt;\n\n\nMake sure it is Genuine ETRG release @ ExtraTorrent.com\n &lt;a href=&quot;\nhttp://extratorrent.cc/&quot; rel=&quot;nofollow&quot; target=&quot;_NEW&quot;&gt;\nhttp://extratorrent.cc/&lt;/a&gt; &lt;a href=&quot;\nhttp://extratorrent.com/&quot; rel=&quot;nofollow&quot; target=&quot;_NEW&quot;&gt;\nhttp://extratorrent.com/&lt;/a&gt; &lt;a href=&quot;\nhttp://etproxy.com/&quot; rel=&quot;nofollow&quot; target=&quot;_NEW&quot;&gt;\nhttp://etproxy.com/&lt;/a&gt; &lt;a href=&quot;\nhttp://extratorrentlive.com/&quot; rel=&quot;nofollow&quot; target=&quot;_NEW&quot;&gt;\nhttp://extratorrentlive.com/&lt;/a&gt; &lt;a href=&quot;\nhttp://extratorrentonline.com/&quot; rel=&quot;nofollow&quot; target=&quot;_NEW&quot;&gt;\nhttp://extratorrentonline.com/&lt;/a&gt;\n\nHelp us by donating with Bitcoin: 1XeH1kKXWYbzZcFHokGiZ4d3MWW5WyXzU",
  "parsed": {
    "xt": "urn:btih:b4e09be176781fd49d9babfa3f0aa17d70e289e6",
    "dn": "The.Boy.Next.Door.2015.BRRip.XviD-ETRG",
    "tr": [
      "udp://exodus.desync.com:6969",
      "udp://open.demonii.com:1337",
      "udp://tracker.coppersurfer.tk:6969",
      "udp://tracker.openbittorrent.com:80"
    ],
    "infoHash": "b4e09be176781fd49d9babfa3f0aa17d70e289e6",
    "infoHashBuffer": {
      "type": "Buffer",
      "data": [
        180,
        224,
        155,
        225,
        118,
        120,
        31,
        212,
        157,
        155,
        171,
        250,
        63,
        10,
        161,
        125,
        112,
        226,
        137,
        230
      ]
    },
    "name": "The.Boy.Next.Door.2015.BRRip.XviD-ETRG",
    "announce": [
      "udp://exodus.desync.com:6969",
      "udp://open.demonii.com:1337",
      "udp://tracker.coppersurfer.tk:6969",
      "udp://tracker.openbittorrent.com:80"
    ],
    "urlList": []
  },
  "previous": 4,
  "peers": 38,
  "last_updated": "2016-12-27T10:51:14.352Z"
}