{"title":"Greys.Anatomy.S11E03.720p.HDTV.X264-DIMENSION[rartv]","uid":11185656,"size":721853299,"categoryP":"video","categoryS":"hd___tv_shows","magnet":"?xt=urn:btih:b82e2e72e4f8e0e323c21ca1885b7b8232984393&amp;dn=Greys.Anatomy.S11E03.720p.HDTV.X264-DIMENSION%5Brartv%5D&amp;tr=udp%3A%2F%2Ftracker.openbittorrent.com%3A80&amp;tr=udp%3A%2F%2Fopen.demonii.com%3A1337&amp;tr=udp%3A%2F%2Ftracker.coppersurfer.tk%3A6969&amp;tr=udp%3A%2F%2Fexodus.desync.com%3A6969","seeders":54,"leechers":14,"uploader":"Drarbg","files":4,"time":1412909831,"description":" &lt;a href=&quot;https://rarbg.com&quot; rel=&quot;nofollow&quot; target=&quot;_NEW&quot;&gt;https://rarbg.com&lt;/a&gt;\n\nGreys.Anatomy.S11E03.720p.HDTV.X264-DIMENSION[rartv]\n-----------------------------------------\nScreens : &lt;a href=&quot;\nhttp://imgcrl.org/v/42684682232143548208/&quot; rel=&quot;nofollow&quot; target=&quot;_NEW&quot;&gt;\nhttp://imgcrl.org/v/42684682232143548208/&lt;/a&gt;\n\n-----------------------------------------\nAuto Media Info :\nVideo Format........: AVC\nCodec ID............: V_MPEG4/ISO/AVC\nLength..............: 43mn4s\nVideo...............: 1280x720 ( 23.976fps )\nBitrate.............: 1682Kbps\nAudio Format........: AC-3\nCodec ID............: A_AC3\nBit rate mode.......: Constant\nBitrate.............: 448Kbps\nChannel(s)..........: 6 channels\n\n","torrent":{"xt":"urn:btih:b82e2e72e4f8e0e323c21ca1885b7b8232984393","amp;dn":"Greys.Anatomy.S11E03.720p.HDTV.X264-DIMENSION%5Brartv%5D","amp;tr":["udp%3A%2F%2Ftracker.openbittorrent.com%3A80","udp%3A%2F%2Fopen.demonii.com%3A1337","udp%3A%2F%2Ftracker.coppersurfer.tk%3A6969","udp%3A%2F%2Fexodus.desync.com%3A6969"],"infoHash":"b82e2e72e4f8e0e323c21ca1885b7b8232984393","infoHashBuffer":{"type":"Buffer","data":[184,46,46,114,228,248,224,227,35,194,28,161,136,91,123,130,50,152,67,147]},"announce":[],"urlList":[]}}