{
  "title": "The.Siege.of.Jadotville.2016.HDRip.XviD.AC3-EVO",
  "uid": 15983125,
  "size": 1510635321,
  "categoryP": "video",
  "categoryS": "movies",
  "magnet": "?xt=urn:btih:c9eb3b28a759ffae9defa5207a68f1a716c91ea9&amp;dn=The.Siege.of.Jadotville.2016.HDRip.XviD.AC3-EVO&amp;tr=udp%3A%2F%2Ftracker.leechers-paradise.org%3A6969&amp;tr=udp%3A%2F%2Fzer0day.ch%3A1337&amp;tr=udp%3A%2F%2Fopen.demonii.com%3A1337&amp;tr=udp%3A%2F%2Ftracker.coppersurfer.tk%3A6969&amp;tr=udp%3A%2F%2Fexodus.desync.com%3A6969",
  "seeders": 637,
  "leechers": 415,
  "uploader": "xxxlavalxxx",
  "files": 9,
  "time": 1475926854,
  "description": "https://extraimago.com/image/wZcM\r\n \nhttp://www.imdb.com/title/tt3922798/\r\n\r\n\r\nIrish Commandant Pat Quinlan leads a stand off with troops against French and Belgian Mercenaries in the Congo during in the early 1960s.\r\n\r\nDirector: Richie Smyth\r\nWriters: Kevin Brodbin, Declan Power (based on the novel by)\r\nStars: Jamie Dornan, Jason O'Mara, Mark Strong \r\nGenres: Action | Drama | Thriller\r\nCountry: Ireland | South Africa\r\nLanguage: English | Irish\r\n\r\n\r\nRELEASE: Jadotville.2016.HDRip.XviD.AC3-EVO                                             \r\n\r\nSOURCE: DEFLATE (Scene)                                               \r\n\r\nViDEO: 1500 kbps XviD -2 Passes              \r\n\r\nRESOLUTiON: 720x304                           \r\n\r\nRUNTiME: 1h47m33sec      \r\n\r\nSUBTiTLES: English when needed (.srt) &amp; Full + French, German, Italian (.srt)                              \r\n\r\nAUDiO: 448 CBR AC-3 5.1       \r\n\r\nLANGUAGE: ENGLiSH                                    \r\n\r\nGREETS: Srkfan &amp; AQOS \r\n\r\nNOTES: Enjoy.   \r\n\r\n \nhttps://extraimago.com/image/wZcU \nhttps://extraimago.com/image/wZcz \nhttps://extraimago.com/image/wZc0 \nhttps://extraimago.com/image/wZcJ \nhttps://extraimago.com/image/wZcK",
  "parsed": {
    "xt": "urn:btih:c9eb3b28a759ffae9defa5207a68f1a716c91ea9",
    "dn": "The.Siege.of.Jadotville.2016.HDRip.XviD.AC3-EVO",
    "tr": [
      "udp://exodus.desync.com:6969",
      "udp://open.demonii.com:1337",
      "udp://tracker.coppersurfer.tk:6969",
      "udp://tracker.leechers-paradise.org:6969",
      "udp://zer0day.ch:1337"
    ],
    "infoHash": "c9eb3b28a759ffae9defa5207a68f1a716c91ea9",
    "infoHashBuffer": {
      "type": "Buffer",
      "data": [
        201,
        235,
        59,
        40,
        167,
        89,
        255,
        174,
        157,
        239,
        165,
        32,
        122,
        104,
        241,
        167,
        22,
        201,
        30,
        169
      ]
    },
    "name": "The.Siege.of.Jadotville.2016.HDRip.XviD.AC3-EVO",
    "announce": [
      "udp://exodus.desync.com:6969",
      "udp://open.demonii.com:1337",
      "udp://tracker.coppersurfer.tk:6969",
      "udp://tracker.leechers-paradise.org:6969",
      "udp://zer0day.ch:1337"
    ],
    "urlList": []
  },
  "previous": 300,
  "peers": 100,
  "last_updated": "2016-12-27T13:02:43.403Z"
}