{
  "title": "Outcast.S01E07.WEB-DL.x264-FUM[ettv]",
  "uid": 15390161,
  "size": 271648521,
  "categoryP": "video",
  "categoryS": "tv_shows",
  "magnet": "?xt=urn:btih:d424bc89bdbd7851e7532c4166d482d7fbad08f9&amp;dn=Outcast.S01E07.WEB-DL.x264-FUM%5Bettv%5D&amp;tr=udp%3A%2F%2Ftracker.leechers-paradise.org%3A6969&amp;tr=udp%3A%2F%2Fzer0day.ch%3A1337&amp;tr=udp%3A%2F%2Fopen.demonii.com%3A1337&amp;tr=udp%3A%2F%2Ftracker.coppersurfer.tk%3A6969&amp;tr=udp%3A%2F%2Fexodus.desync.com%3A6969",
  "seeders": 254,
  "leechers": 11,
  "uploader": "ettv",
  "files": 2,
  "time": 1469326708,
  "description": "\n                ettv - ExtraTorrent TV Shows\r\n\n                        \n                Outcast.S01E07.WEB-DL.x264-FUM \r\n\n                        \n                [Format]:    MPEG-4\n[Duration]:    49mn 21s\n[Resolution]:  720 x 404 pixels\n[Display aspect ratio]:    16:9\n[Frame rate mode]:    Constant\n[Frame rate]:    23.976 fps\n\r\n\n                #ettv -&gt; To avoid fakes, ALWAYS check that the torrent was added by ettv\r\n\n                http://extratorrent.cc/\r\n\n                        \n                Help us by donating with Bitcoin: 1MbtePmWNM13SEkQgmxF6RSvfaXugF7rpz\r\n\nScreens...\r \nhttp://extraimago.com/image/aWEC",
  "parsed": {
    "xt": "urn:btih:d424bc89bdbd7851e7532c4166d482d7fbad08f9",
    "dn": "Outcast.S01E07.WEB-DL.x264-FUM[ettv]",
    "tr": [
      "udp://exodus.desync.com:6969",
      "udp://open.demonii.com:1337",
      "udp://tracker.coppersurfer.tk:6969",
      "udp://tracker.leechers-paradise.org:6969",
      "udp://zer0day.ch:1337"
    ],
    "infoHash": "d424bc89bdbd7851e7532c4166d482d7fbad08f9",
    "infoHashBuffer": {
      "type": "Buffer",
      "data": [
        212,
        36,
        188,
        137,
        189,
        189,
        120,
        81,
        231,
        83,
        44,
        65,
        102,
        212,
        130,
        215,
        251,
        173,
        8,
        249
      ]
    },
    "name": "Outcast.S01E07.WEB-DL.x264-FUM[ettv]",
    "announce": [
      "udp://exodus.desync.com:6969",
      "udp://open.demonii.com:1337",
      "udp://tracker.coppersurfer.tk:6969",
      "udp://tracker.leechers-paradise.org:6969",
      "udp://zer0day.ch:1337"
    ],
    "urlList": []
  },
  "previous": 265,
  "peers": 201,
  "last_updated": "2016-12-25T14:57:02.020Z"
}