{
  "title": "Jordan Belfort - Straight Line Persuasion",
  "uid": 9587957,
  "size": 5988092464,
  "categoryP": "other",
  "categoryS": "other",
  "magnet": "?xt=urn:btih:d4c3f01db974ede1d4415120e0b89d0b432ab090&amp;dn=Jordan+Belfort+-+Straight+Line+Persuasion&amp;tr=udp%3A%2F%2Ftracker.openbittorrent.com%3A80&amp;tr=udp%3A%2F%2Fopen.demonii.com%3A1337&amp;tr=udp%3A%2F%2Ftracker.coppersurfer.tk%3A6969&amp;tr=udp%3A%2F%2Fexodus.desync.com%3A6969",
  "seeders": 61,
  "leechers": 6,
  "uploader": "ramazone2",
  "files": 12,
  "time": 1391847074,
  "description": "Jordan Belfort the 'Wolf of Wall Street' - Straight Line Persuasion Sales System",
  "parsed": {
    "xt": "urn:btih:d4c3f01db974ede1d4415120e0b89d0b432ab090",
    "dn": "Jordan Belfort - Straight Line Persuasion",
    "tr": [
      "udp://exodus.desync.com:6969",
      "udp://open.demonii.com:1337",
      "udp://tracker.coppersurfer.tk:6969",
      "udp://tracker.openbittorrent.com:80"
    ],
    "infoHash": "d4c3f01db974ede1d4415120e0b89d0b432ab090",
    "infoHashBuffer": {
      "type": "Buffer",
      "data": [
        212,
        195,
        240,
        29,
        185,
        116,
        237,
        225,
        212,
        65,
        81,
        32,
        224,
        184,
        157,
        11,
        67,
        42,
        176,
        144
      ]
    },
    "name": "Jordan Belfort - Straight Line Persuasion",
    "announce": [
      "udp://exodus.desync.com:6969",
      "udp://open.demonii.com:1337",
      "udp://tracker.coppersurfer.tk:6969",
      "udp://tracker.openbittorrent.com:80"
    ],
    "urlList": []
  },
  "previous": 67,
  "peers": 50,
  "last_updated": "2016-12-25T15:01:08.743Z"
}