{
  "title": "Ben Howard - 2012 - The Burgh Island - EP (320)[REQ]",
  "uid": 9117756,
  "size": 56642826,
  "categoryP": "audio",
  "categoryS": "music",
  "magnet": "?xt=urn:btih:dc6e69648465d4faf995660e7d7dd4b9ae6577b6&amp;dn=Ben+Howard+-+2012+-+The+Burgh+Island+-+EP+%28320%29%5BREQ%5D&amp;tr=udp%3A%2F%2Ftracker.openbittorrent.com%3A80&amp;tr=udp%3A%2F%2Fopen.demonii.com%3A1337&amp;tr=udp%3A%2F%2Ftracker.coppersurfer.tk%3A6969&amp;tr=udp%3A%2F%2Fexodus.desync.com%3A6969",
  "seeders": 44,
  "leechers": 1,
  "uploader": "mindcrasher",
  "files": -1,
  "time": 1383059705,
  "description": "01. Esmerelda (4:45)\n02. Oats In The Water (4:59)\n03. To Be Alone (5:38)\n04. Burgh Island (8:13)",
  "parsed": {
    "xt": "urn:btih:dc6e69648465d4faf995660e7d7dd4b9ae6577b6",
    "dn": "Ben Howard - 2012 - The Burgh Island - EP (320)[REQ]",
    "tr": [
      "udp://exodus.desync.com:6969",
      "udp://open.demonii.com:1337",
      "udp://tracker.coppersurfer.tk:6969",
      "udp://tracker.openbittorrent.com:80"
    ],
    "infoHash": "dc6e69648465d4faf995660e7d7dd4b9ae6577b6",
    "infoHashBuffer": {
      "type": "Buffer",
      "data": [
        220,
        110,
        105,
        100,
        132,
        101,
        212,
        250,
        249,
        149,
        102,
        14,
        125,
        125,
        212,
        185,
        174,
        101,
        119,
        182
      ]
    },
    "name": "Ben Howard - 2012 - The Burgh Island - EP (320)[REQ]",
    "announce": [
      "udp://exodus.desync.com:6969",
      "udp://open.demonii.com:1337",
      "udp://tracker.coppersurfer.tk:6969",
      "udp://tracker.openbittorrent.com:80"
    ],
    "urlList": []
  },
  "previous": 45,
  "peers": 50,
  "last_updated": "2016-12-25T15:44:56.315Z"
}