{
  "title": "Family Guy S12E15 HDTV x264-EXCELLENCE [eztv]",
  "uid": 9858025,
  "size": 68917446,
  "categoryP": "video",
  "categoryS": "tv_shows",
  "magnet": "?xt=urn:btih:e6cbb33fbb70ec7d2d62e7a6d67a9586a409dead&amp;dn=Family+Guy+S12E15+HDTV+x264-EXCELLENCE+%5Beztv%5D&amp;tr=udp%3A%2F%2Ftracker.openbittorrent.com%3A80&amp;tr=udp%3A%2F%2Fopen.demonii.com%3A1337&amp;tr=udp%3A%2F%2Ftracker.coppersurfer.tk%3A6969&amp;tr=udp%3A%2F%2Fexodus.desync.com%3A6969",
  "seeders": 67,
  "leechers": 7,
  "uploader": "eztv",
  "files": 1,
  "time": 1396244906,
  "description": "Help us by donating with Bitcoin: 1EZTVaGQ6UsjYJ9fwqGnd45oZ6HGT7WKZd\n\n#EZTV -&gt; To avoid fakes, ALWAYS check that the torrent was added by eztv.\n &lt;a href=&quot;\nhttps://eztv.it/&quot; rel=&quot;nofollow&quot; target=&quot;_NEW&quot;&gt;\nhttps://eztv.it/&lt;/a&gt;\n\nEpisode: Family Guy S12E15 HDTV x264-EXCELLENCE\nScreenshots:\n\n\n",
  "parsed": {
    "xt": "urn:btih:e6cbb33fbb70ec7d2d62e7a6d67a9586a409dead",
    "dn": "Family Guy S12E15 HDTV x264-EXCELLENCE [eztv]",
    "tr": [
      "udp://exodus.desync.com:6969",
      "udp://open.demonii.com:1337",
      "udp://tracker.coppersurfer.tk:6969",
      "udp://tracker.openbittorrent.com:80"
    ],
    "infoHash": "e6cbb33fbb70ec7d2d62e7a6d67a9586a409dead",
    "infoHashBuffer": {
      "type": "Buffer",
      "data": [
        230,
        203,
        179,
        63,
        187,
        112,
        236,
        125,
        45,
        98,
        231,
        166,
        214,
        122,
        149,
        134,
        164,
        9,
        222,
        173
      ]
    },
    "name": "Family Guy S12E15 HDTV x264-EXCELLENCE [eztv]",
    "announce": [
      "udp://exodus.desync.com:6969",
      "udp://open.demonii.com:1337",
      "udp://tracker.coppersurfer.tk:6969",
      "udp://tracker.openbittorrent.com:80"
    ],
    "urlList": []
  },
  "previous": 74,
  "peers": 39,
  "last_updated": "2016-12-25T16:46:29.884Z"
}