{
  "title": "MUKD-391 Untitled Not Convey A Character, The Charm Of This Beau",
  "uid": 15831525,
  "size": 3596469291,
  "categoryP": "porn",
  "categoryS": "movie_clips",
  "magnet": "?xt=urn:btih:f2b3d78932b6a1975567171a9efc52a302231e7d&amp;dn=MUKD-391+Untitled+Not+Convey+A+Character%2C+The+Charm+Of+This+Beau&amp;tr=udp%3A%2F%2Ftracker.leechers-paradise.org%3A6969&amp;tr=udp%3A%2F%2Fzer0day.ch%3A1337&amp;tr=udp%3A%2F%2Fopen.demonii.com%3A1337&amp;tr=udp%3A%2F%2Ftracker.coppersurfer.tk%3A6969&amp;tr=udp%3A%2F%2Fexodus.desync.com%3A6969",
  "seeders": 70,
  "leechers": 82,
  "uploader": "texile911",
  "files": 1,
  "time": 1473918647,
  "description": "http://imgplus.ru/img-57da1aac141d0.html \nhttp://imgplus.ru/img-57da1aac29f42.html\r\n\r\nSEX01 - Daily Free Porn \r\n  \nhttp://sex01.org",
  "parsed": {
    "xt": "urn:btih:f2b3d78932b6a1975567171a9efc52a302231e7d",
    "dn": "MUKD-391 Untitled Not Convey A Character, The Charm Of This Beau",
    "tr": [
      "udp://exodus.desync.com:6969",
      "udp://open.demonii.com:1337",
      "udp://tracker.coppersurfer.tk:6969",
      "udp://tracker.leechers-paradise.org:6969",
      "udp://zer0day.ch:1337"
    ],
    "infoHash": "f2b3d78932b6a1975567171a9efc52a302231e7d",
    "infoHashBuffer": {
      "type": "Buffer",
      "data": [
        242,
        179,
        215,
        137,
        50,
        182,
        161,
        151,
        85,
        103,
        23,
        26,
        158,
        252,
        82,
        163,
        2,
        35,
        30,
        125
      ]
    },
    "name": "MUKD-391 Untitled Not Convey A Character, The Charm Of This Beau",
    "announce": [
      "udp://exodus.desync.com:6969",
      "udp://open.demonii.com:1337",
      "udp://tracker.coppersurfer.tk:6969",
      "udp://tracker.leechers-paradise.org:6969",
      "udp://zer0day.ch:1337"
    ],
    "urlList": []
  },
  "previous": 152,
  "peers": 58,
  "last_updated": "2016-12-25T17:57:29.675Z"
}