{"title":"Furious 7 2015 CAM x264-RARBG","uid":11795453,"size":2028508580,"categoryP":"video","categoryS":"movies","magnet":"?xt=urn:btih:fb1233a201494a0e82a64b69be06b1c4b3c3dca3&amp;dn=Furious+7+2015+CAM+x264-RARBG&amp;tr=udp%3A%2F%2Ftracker.openbittorrent.com%3A80&amp;tr=udp%3A%2F%2Fopen.demonii.com%3A1337&amp;tr=udp%3A%2F%2Ftracker.coppersurfer.tk%3A6969&amp;tr=udp%3A%2F%2Fexodus.desync.com%3A6969","seeders":203,"leechers":27,"uploader":"makintos13","files":4,"time":1428106884,"description":"screen:\n &lt;a href=&quot;\nhttp://imgmak.com/pP&quot; rel=&quot;nofollow&quot; target=&quot;_NEW&quot;&gt;\nhttp://imgmak.com/pP&lt;/a&gt;\n &lt;a href=&quot;\nhttp://imgmak.com/pY&quot; rel=&quot;nofollow&quot; target=&quot;_NEW&quot;&gt;\nhttp://imgmak.com/pY&lt;/a&gt;\n &lt;a href=&quot;\nhttp://imgmak.com/p0&quot; rel=&quot;nofollow&quot; target=&quot;_NEW&quot;&gt;\nhttp://imgmak.com/p0&lt;/a&gt;\n &lt;a href=&quot;\nhttp://imgmak.com/pA&quot; rel=&quot;nofollow&quot; target=&quot;_NEW&quot;&gt;\nhttp://imgmak.com/pA&lt;/a&gt;\n &lt;a href=&quot;\nhttp://imgmak.com/pD&quot; rel=&quot;nofollow&quot; target=&quot;_NEW&quot;&gt;\nhttp://imgmak.com/pD&lt;/a&gt;\n &lt;a href=&quot;\nhttp://imgmak.com/pf&quot; rel=&quot;nofollow&quot; target=&quot;_NEW&quot;&gt;\nhttp://imgmak.com/pf&lt;/a&gt;\n &lt;a href=&quot;\nhttp://imgmak.com/pE&quot; rel=&quot;nofollow&quot; target=&quot;_NEW&quot;&gt;\nhttp://imgmak.com/pE&lt;/a&gt;\n\n\nFurious.7.2015.CAM.x264-RARBG\n\nNotes : \nWe know we dont do cams anymore but we decided to do this one!\nFiltered the available sources. Some dark scenes are very dark. First 2 minutes are italian. Thats all","torrent":{"xt":"urn:btih:fb1233a201494a0e82a64b69be06b1c4b3c3dca3","amp;dn":"Furious+7+2015+CAM+x264-RARBG","amp;tr":["udp%3A%2F%2Ftracker.openbittorrent.com%3A80","udp%3A%2F%2Fopen.demonii.com%3A1337","udp%3A%2F%2Ftracker.coppersurfer.tk%3A6969","udp%3A%2F%2Fexodus.desync.com%3A6969"],"infoHash":"fb1233a201494a0e82a64b69be06b1c4b3c3dca3","infoHashBuffer":{"type":"Buffer","data":[251,18,51,162,1,73,74,14,130,166,75,105,190,6,177,196,179,195,220,163]},"announce":[],"urlList":[]}}